notsotuf/__init__.py
notsotuf/client.py
notsotuf/common.py
notsotuf/repo.py
notsotuf/utils/__init__.py
notsotuf/utils/windows.py
notsotuf-2022.0.dist-info/LICENSE
notsotuf-2022.0.dist-info/METADATA
notsotuf-2022.0.dist-info/WHEEL
notsotuf-2022.0.dist-info/top_level.txt
notsotuf-2022.0.dist-info/RECORD
