Metadata-Version: 2.1
Name: notsotuf
Version: 2022.0
Summary: Automated updates for stand-alone Python applications, built upon python-tuf.
Home-page: https://github.com/dennisvang/notsotuf
Author: dennisvang
Author-email: djvg@protonmail.com
License: UNKNOWN
Project-URL: Bug Tracker, https://github.com/dennisvang/notsotuf/issues
Platform: UNKNOWN
Classifier: Programming Language :: Python :: 3
Classifier: License :: OSI Approved :: MIT License
Classifier: Operating System :: OS Independent
Requires-Python: >=3.8
License-File: LICENSE
Requires-Dist: bsdiff4 (==1.2.*)
Requires-Dist: packaging (==21.*)
Requires-Dist: securesystemslib[crypto,pynacl] (==0.22.*)
Requires-Dist: tuf (==1.0.*)
